setup.py
AuthzPolicyPlugin.egg-info/PKG-INFO
AuthzPolicyPlugin.egg-info/SOURCES.txt
AuthzPolicyPlugin.egg-info/dependency_links.txt
AuthzPolicyPlugin.egg-info/entry_points.txt
AuthzPolicyPlugin.egg-info/not-zip-safe
AuthzPolicyPlugin.egg-info/top_level.txt
authzpolicy/__init__.py
authzpolicy/api.py