Metadata-Version: 1.0
Name: AuthzPolicyPlugin
Version: 0.1
Summary: Trac's authz_policy with some improvements.
Home-page: http://mitar.tnode.com/
Author: Mitar
Author-email: mitar.trac@tnode.com
License: GPLv3
Keywords: trac plugin
Platform: UNKNOWN
